LICENSE
MANIFEST.in
README.md
requirements.txt
setup.py
solarDeltaSolMQTT/__init__.py
solarDeltaSolMQTT/__main__.py
solarDeltaSolMQTT/config.py
solarDeltaSolMQTT/moving_average.py
solarDeltaSolMQTT/mqtt_client.py
solarDeltaSolMQTT/vbus.py
solarDeltaSolMQTT.egg-info/PKG-INFO
solarDeltaSolMQTT.egg-info/SOURCES.txt
solarDeltaSolMQTT.egg-info/dependency_links.txt
solarDeltaSolMQTT.egg-info/entry_points.txt
solarDeltaSolMQTT.egg-info/requires.txt
solarDeltaSolMQTT.egg-info/top_level.txt
tests/__init__.py
tests/moving_average.py
tests/test.py